dynlog/Logger.py
dynlog/__init__.py
dynlog/logger_interface.py
dynlog/logger_manager.py
dynlog-0.0.1.dist-info/LICENSE
dynlog-0.0.1.dist-info/WHEEL
dynlog-0.0.1.dist-info/METADATA
dynlog-0.0.1.dist-info/RECORD
